mdformat/__init__.py
mdformat/__main__.py
mdformat/_api.py
mdformat/_cli.py
mdformat/_compat.py
mdformat/_conf.py
mdformat/_util.py
mdformat/plugins.py
mdformat/py.typed
mdformat/codepoints/__init__.py
mdformat/codepoints/_unicode_punctuation.py
mdformat/codepoints/_unicode_whitespace.py
mdformat/renderer/__init__.py
mdformat/renderer/_context.py
mdformat/renderer/_tree.py
mdformat/renderer/_util.py
mdformat/renderer/typing.py
mdformat-0.7.20.dist-info/LICENSE
mdformat-0.7.20.dist-info/METADATA
mdformat-0.7.20.dist-info/WHEEL
mdformat-0.7.20.dist-info/entry_points.txt
mdformat-0.7.20.dist-info/top_level.txt
mdformat-0.7.20.dist-info/RECORD
