Metadata-Version: 2.1
Name: mdformat
Version: 0.7.20
Summary: CommonMark compliant Markdown formatter
Author-email: Taneli Hukkinen <hukkin@users.noreply.github.com>
License: MIT License
Project-URL: Homepage, https://github.com/hukkin/mdformat
Project-URL: Documentation, https://mdformat.readthedocs.io
Project-URL: Style guide, https://mdformat.readthedocs.io/en/stable/users/style.html
Project-URL: Changelog, https://mdformat.readthedocs.io/en/stable/users/changelog.html
Keywords: mdformat,markdown,commonmark,formatter,pre-commit
Classifier: Environment :: Console
Classifier: License :: OSI Approved :: MIT License
Classifier: Operating System :: MacOS
Classifier: Operating System :: Microsoft :: Windows
Classifier: Operating System :: POSIX :: Linux
Classifier: Topic :: Documentation
Classifier: Topic :: Software Development :: Libraries :: Python Modules
Classifier: Topic :: Text Processing :: Markup
Classifier: Typing :: Typed
Requires-Python: >=3.9
License-File: LICENSE
Requires-Dist: markdown-it-py<4.0.0,>=1.0.0
Requires-Dist: tomli>=1.1.0; python_version < "3.11"
Requires-Dist: importlib-metadata>=3.6.0; python_version < "3.10"
